postolit/__init__.py
postolit/postolit.py
postolit-0.0.7.dist-info/LICENSE
postolit-0.0.7.dist-info/METADATA
postolit-0.0.7.dist-info/WHEEL
postolit-0.0.7.dist-info/top_level.txt
postolit-0.0.7.dist-info/RECORD
