Metadata-Version: 2.1
Name: postolit
Version: 0.0.7
Summary: Postoperative Library for Image Transformation
Home-page: https://github.com/APostolit
Author: prof. Anatoly Postolit
Author-email: anat_post@mail.ru
License: LICENSE
Platform: UNKNOWN
Classifier: Programming Language :: Python :: 3.7
Classifier: License :: OSI Approved :: MIT License
Classifier: Operating System :: OS Independent
Requires-Python: >=3.7
Requires-Dist: opencv-python (<=4.4.0.46)
Requires-Dist: numpy (<=1.19.4)
